gshapa/__init__.py
gshapa/gshapa.py
gshapa-0.1.10.dist-info/METADATA
gshapa-0.1.10.dist-info/WHEEL
gshapa-0.1.10.dist-info/licenses/LICENSE
gshapa-0.1.10.dist-info/RECORD
