Metadata-Version: 2.4
Name: gshapa
Version: 0.1.10
Summary: Gene Set Analysis for Single-Cell RNA-seq Using Random Forest and SHAP Valuese
Project-URL: Homepage, https://gitlab.com/bf2i/gshapa
Project-URL: Issues, https://gitlab.com/bf2i/gshapa/issues
Author-email: Sara Khademioureh <khademio@ualberta.ca>, Sergio Peignier <sergio.peignier@insa-lyon.fr>
License-File: LICENSE
Keywords: Gene Set Analysis,Random Forest,SHAP values
Classifier: License :: OSI Approved :: MIT License
Classifier: Operating System :: OS Independent
Classifier: Programming Language :: Python :: 3
Requires-Python: >=3.8
